{
    "configurations": [
        {
            "browse": {
                "databaseFilename": "",
                "limitSymbolsToIncludedHeaders": true
            },
            "includePath": [
                "/home/mcres/ignition/install/include/**",
                "/opt/ros/melodic/include/**",
                "/home/mcres/ws_ros/src/using_markers/include/**",
                "/usr/include/**"
            ],
            "name": "ROS",
            "intelliSenseMode": "gcc-x64",
            "compilerPath": "/usr/bin/gcc",
            "cStandard": "c11",
            "cppStandard": "gnu++14"
        }
    ],
    "version": 4
}